multicounter/__init__.py
multicounter/multicounter.py
multicounter/py.typed
multicounter-0.2.0.dist-info/LICENSE
multicounter-0.2.0.dist-info/METADATA
multicounter-0.2.0.dist-info/WHEEL
multicounter-0.2.0.dist-info/RECORD
