Metadata-Version: 2.1
Name: multicounter
Version: 0.2.0
Summary: A simple, elegant counter with support for counting multiple things at once.
Home-page: https://github.com/thehale/multicounter
License: MPL-2.0
Keywords: counter,statistics
Author: Joseph Hale
Author-email: me@jhale.dev
Requires-Python: >=3.8,<4.0
Classifier: License :: OSI Approved
Classifier: Programming Language :: Python :: 3
Classifier: Programming Language :: Python :: 3.8
Classifier: Programming Language :: Python :: 3.9
Classifier: Programming Language :: Python :: 3.10
Classifier: Programming Language :: Python :: 3.11
Classifier: Programming Language :: Python :: 3.12
Project-URL: Documentation, https://github.com/thehale/multicounter
Project-URL: Repository, https://github.com/thehale/multicounter
